nextapm/__init__.py
nextapm/lib/__init__.py
nextapm/lib/constants.py
nextapm/lib/logger.py
nextapm/lib/test_util.py
nextapm/lib/util.py
nextapm/lib/data/__init__.py
nextapm/lib/data/context.py
nextapm/lib/data/test_context.py
nextapm/lib/data/test_txn.py
nextapm/lib/data/transport.py
nextapm/lib/data/txn.py
nextapm/lib/instrument/__init__.py
nextapm/lib/instrument/modules.py
nextapm/lib/instrument/wrapper.py
nextapm-1.0.1.dist-info/METADATA
nextapm-1.0.1.dist-info/WHEEL
nextapm-1.0.1.dist-info/top_level.txt
nextapm-1.0.1.dist-info/RECORD
