Metadata-Version: 2.1
Name: nextapm
Version: 1.0.1
Summary: Monitor vercel serverless python api
Home-page: https://nextapm.dev
Author: Chan Anan
Author-email: chan@nextapm.dev
License: MIT
Platform: UNKNOWN
Requires-Python: >=3.6
Requires-Dist: requests
